mosaik_components/influxdb2/__init__.py
mosaik_components/influxdb2/writer.py
mosaik_influxdb2-0.4.0.dist-info/METADATA
mosaik_influxdb2-0.4.0.dist-info/WHEEL
mosaik_influxdb2-0.4.0.dist-info/licenses/LICENSE
mosaik_influxdb2-0.4.0.dist-info/RECORD
