Metadata-Version: 2.4
Name: mosaik-influxdb2
Version: 0.4.0
Summary: An adapter to connect mosaik with InfluxDB 2
License: MIT
License-File: LICENSE
Author: Eike Schulte
Author-email: eike.schulte@offis.de
Requires-Python: >=3.8,<4.0
Classifier: License :: OSI Approved :: MIT License
Classifier: Programming Language :: Python :: 3
Classifier: Programming Language :: Python :: 3.8
Classifier: Programming Language :: Python :: 3.9
Classifier: Programming Language :: Python :: 3.10
Classifier: Programming Language :: Python :: 3.11
Classifier: Programming Language :: Python :: 3.12
Classifier: Programming Language :: Python :: 3.13
Classifier: Programming Language :: Python :: 3.14
Requires-Dist: influxdb-client (>=1.35.0,<2.0.0)
Requires-Dist: loguru (>=0.7.3,<0.8.0)
Requires-Dist: mosaik-api-v3 (>=3.0.13,<4.0.0)
